django_nanoid/__init__.py
django_nanoid/models.py
django_nanoid/serializers.py
django_nanoid-0.0.2.dist-info/AUTHORS.txt
django_nanoid-0.0.2.dist-info/LICENSE
django_nanoid-0.0.2.dist-info/METADATA
django_nanoid-0.0.2.dist-info/WHEEL
django_nanoid-0.0.2.dist-info/top_level.txt
django_nanoid-0.0.2.dist-info/RECORD
