Metadata-Version: 2.1
Name: django-nanoid
Version: 0.0.2
Summary: A tiny, secure, URL-friendly, unique string ID generator support in Django
Home-page: https://github.com/yosephbernandus/django-nanoid
Author: Yoseph Bernandus
Author-email: yosephbernandus@gmail.com
License: Apache 2.0
Platform: UNKNOWN
Classifier: Development Status :: 4 - Beta
Classifier: Environment :: Web Environment
Classifier: Framework :: Django
Classifier: Intended Audience :: Developers
Classifier: License :: OSI Approved :: Apache Software License
Classifier: Operating System :: OS Independent
Classifier: Programming Language :: Python
Classifier: Programming Language :: Python :: 3
Classifier: Programming Language :: Python :: 3.5
Classifier: Programming Language :: Python :: 3.6
Classifier: Programming Language :: Python :: 3.7
Classifier: Programming Language :: Python :: 3.8
Classifier: Topic :: Internet :: WWW/HTTP
Classifier: Topic :: Software Development :: Libraries :: Python Modules
Requires-Dist: Django (>=1.9)
Requires-Dist: nanoid
Requires-Dist: djangorestframework (>=3.0.0)
Provides-Extra: dev
Requires-Dist: pytest (>=7.0) ; extra == 'dev'
Requires-Dist: twine (>=4.0.2) ; extra == 'dev'
